LICENSE
MANIFEST.in
README.md
requirements-dev.txt
requirements.txt
setup.py
ibm_cloud_networking_services/__init__.py
ibm_cloud_networking_services/alerts_v1.py
ibm_cloud_networking_services/caching_api_v1.py
ibm_cloud_networking_services/cis_ip_api_v1.py
ibm_cloud_networking_services/common.py
ibm_cloud_networking_services/custom_pages_v1.py
ibm_cloud_networking_services/direct_link_provider_v2.py
ibm_cloud_networking_services/direct_link_v1.py
ibm_cloud_networking_services/dns_record_bulk_v1.py
ibm_cloud_networking_services/dns_records_v1.py
ibm_cloud_networking_services/dns_svcs_v1.py
ibm_cloud_networking_services/dns_zones_v1.py
ibm_cloud_networking_services/filters_v1.py
ibm_cloud_networking_services/firewall_access_rules_v1.py
ibm_cloud_networking_services/firewall_api_v1.py
ibm_cloud_networking_services/firewall_rules_v1.py
ibm_cloud_networking_services/global_load_balancer_events_v1.py
ibm_cloud_networking_services/global_load_balancer_monitor_v1.py
ibm_cloud_networking_services/global_load_balancer_pools_v0.py
ibm_cloud_networking_services/global_load_balancer_v1.py
ibm_cloud_networking_services/global_load_balancers_v1.py
ibm_cloud_networking_services/page_rule_api_v1.py
ibm_cloud_networking_services/permitted_networks_for_dns_zones_v1.py
ibm_cloud_networking_services/range_applications_v1.py
ibm_cloud_networking_services/resource_records_v1.py
ibm_cloud_networking_services/routing_v1.py
ibm_cloud_networking_services/security_events_api_v1.py
ibm_cloud_networking_services/ssl_certificate_api_v1.py
ibm_cloud_networking_services/transit_gateway_apis_v1.py
ibm_cloud_networking_services/user_agent_blocking_rules_v1.py
ibm_cloud_networking_services/version.py
ibm_cloud_networking_services/waf_api_v1.py
ibm_cloud_networking_services/waf_rule_groups_api_v1.py
ibm_cloud_networking_services/waf_rule_packages_api_v1.py
ibm_cloud_networking_services/waf_rules_api_v1.py
ibm_cloud_networking_services/webhooks_v1.py
ibm_cloud_networking_services.egg-info/PKG-INFO
ibm_cloud_networking_services.egg-info/SOURCES.txt
ibm_cloud_networking_services.egg-info/dependency_links.txt
ibm_cloud_networking_services.egg-info/requires.txt
ibm_cloud_networking_services.egg-info/top_level.txt
ibm_cloud_networking_services.egg-info/zip-safe