Metadata-Version: 2.1
Name: ibm-cloud-networking-services
Version: 0.24.0
Summary: Python client library for IBM Cloud Networking Services
Home-page: https://github.com/IBM/networking-python-sdk
Author: IBM
Author-email: devexdev@us.ibm.com
License: Apache 2.0
Keywords: ibm_cloud_networking_services
Platform: UNKNOWN
Classifier: Programming Language :: Python
Classifier: Programming Language :: Python :: 3
Classifier: Programming Language :: Python :: 3.7
Classifier: Programming Language :: Python :: 3.8
Classifier: Programming Language :: Python :: 3.9
Classifier: Programming Language :: Python :: 3.10
Classifier: Development Status :: 4 - Beta
Classifier: Intended Audience :: Developers
Classifier: License :: OSI Approved :: Apache Software License
Classifier: Operating System :: OS Independent
Classifier: Topic :: Software Development :: Libraries :: Python Modules
Classifier: Topic :: Software Development :: Libraries :: Application Frameworks
License-File: LICENSE
